{
  "indexes": [
    {
      "collectionGroup": "entries",
      "queryScope": "COLLECTION",
      "fields": [
        {
          "fieldPath": "score",
          "order": "DESCENDING"
        },
        {
          "fieldPath": "updatedAt",
          "order": "ASCENDING"
        }
      ]
    },
    {
      "collectionGroup": "entries",
      "queryScope": "COLLECTION",
      "fields": [
        {
          "fieldPath": "weekKey",
          "order": "ASCENDING"
        },
        {
          "fieldPath": "score",
          "order": "DESCENDING"
        }
      ]
    },
    {
      "collectionGroup": "dailyStudies",
      "queryScope": "COLLECTION",
      "fields": [
        {
          "fieldPath": "status",
          "order": "ASCENDING"
        },
        {
          "fieldPath": "dateKey",
          "order": "DESCENDING"
        }
      ]
    },
    {
      "collectionGroup": "rewards",
      "queryScope": "COLLECTION",
      "fields": [
        {
          "fieldPath": "isActive",
          "order": "ASCENDING"
        },
        {
          "fieldPath": "sortOrder",
          "order": "ASCENDING"
        }
      ]
    }
  ],
  "fieldOverrides": []
}
